streamlit_jwt_authenticator/__init__.py
streamlit_jwt_authenticator/jwt.py
streamlit_jwt_authenticator/utils.py
streamlit_jwt_authenticator-0.0.2.dist-info/LICENSE
streamlit_jwt_authenticator-0.0.2.dist-info/METADATA
streamlit_jwt_authenticator-0.0.2.dist-info/WHEEL
streamlit_jwt_authenticator-0.0.2.dist-info/top_level.txt
streamlit_jwt_authenticator-0.0.2.dist-info/RECORD
