Metadata-Version: 2.1
Name: streamlit-jwt-authenticator
Version: 0.0.2
Summary: An authentication module to add JWT authentication via API for Streamlit applications
Home-page: https://github.com/YusufBerki/streamlit-jwt-authenticator
Author: Yusuf Berki YAZICIOĞLU
Author-email: mail@yusufberki.net
License: Apache-2.0
Keywords: streamlit,jwt,authentication
Classifier: Development Status :: 3 - Alpha
Classifier: Environment :: Console
Classifier: Environment :: Web Environment
Classifier: Intended Audience :: Developers
Classifier: Intended Audience :: Science/Research
Classifier: Topic :: Database :: Front-Ends
Classifier: Topic :: Scientific/Engineering :: Information Analysis
Classifier: Topic :: Scientific/Engineering :: Visualization
Classifier: Topic :: Software Development :: Libraries :: Application Frameworks
Classifier: Topic :: Software Development :: Widget Sets
Classifier: License :: OSI Approved :: Apache Software License
Classifier: Programming Language :: Python :: 3.8
Classifier: Programming Language :: Python :: 3.9
Classifier: Programming Language :: Python :: 3.10
Classifier: Programming Language :: Python :: 3.11
Classifier: Programming Language :: Python :: 3.12
License-File: LICENSE
Requires-Dist: streamlit
Requires-Dist: extra-streamlit-components
